{"GlobalPropertiesHash":"2ilJ2M8+ZdH0swl4cXFj9Ji8kay0R08ISE/fEc+OL0o=","FingerprintPatternsHash":"8ZRc1sGeVrPBx4lD717BgRaQekyh78QKV9SKsdt638U=","PropertyOverridesHash":"8ZRc1sGeVrPBx4lD717BgRaQekyh78QKV9SKsdt638U=","InputHashes":["Ck6Kr8lh6DTq51aXsWjhMukvsJbKpfHh8\u002BbF7IC8kmg=","ze6epOL55CFc5Sqyh\u002B19FQ/L\u002BND9NS0pldOTm6ZREZE=","xNyi3BnNDzd7DkPrP4C\u002BGZJHFXNF/hOQrz1fYDJyaoY=","xkvCHP05R1a62VKwIjCz949jtXiRiOh1AkuXYpMURyY=","b9B6oPIK961\u002BI7DjvvftK/YG\u002BDSKes8RzH/5iXAlujY=","/bCXn7HbrUgRdAT\u002BgQmRMvxLqbmR082TwgtYeplJ/yI=","ZbgnHujwvCSID\u002B/9zhC5j0FgaRcc\u002BeHWGNJUhKgLx3g="],"CachedAssets":{"Ck6Kr8lh6DTq51aXsWjhMukvsJbKpfHh8\u002BbF7IC8kmg=":{"Identity":"D:\\BLAZOR_ACC\\MyBlazorApp\\MyBlazorApp\\obj\\Debug\\net9.0\\compressed\\ptv96fzqh3-da95v2qkru.gz","SourceId":"MyBlazorApp","SourceType":"Discovered","ContentRoot":"D:\\BLAZOR_ACC\\MyBlazorApp\\MyBlazorApp\\obj\\Debug\\net9.0\\compressed\\","BasePath":"_content/MyBlazorApp","RelativePath":"app#[.{fingerprint=da95v2qkru}]?.css.gz","AssetKind":"All","AssetMode":"All","AssetRole":"Alternative","AssetMergeBehavior":null,"AssetMergeSource":"","RelatedAsset":"D:\\BLAZOR_ACC\\MyBlazorApp\\MyBlazorApp\\wwwroot\\app.css","AssetTraitName":"Content-Encoding","AssetTraitValue":"gzip","Fingerprint":"35bsr2s5bp","Integrity":"Z2oZxhy3yCVx4TNMrDOMMpGuoPS7gb7KEuo/dm8OHbc=","CopyToOutputDirectory":"Never","CopyToPublishDirectory":"PreserveNewest","OriginalItemSpec":"D:\\BLAZOR_ACC\\MyBlazorApp\\MyBlazorApp\\wwwroot\\app.css","FileLength":1481,"LastWriteTime":"2025-12-10T00:22:59.7712552+00:00"},"ze6epOL55CFc5Sqyh\u002B19FQ/L\u002BND9NS0pldOTm6ZREZE=":{"Identity":"D:\\BLAZOR_ACC\\MyBlazorApp\\MyBlazorApp\\obj\\Debug\\net9.0\\compressed\\iyvv8stkq0-bpk8xqwxhs.gz","SourceId":"MyBlazorApp","SourceType":"Discovered","ContentRoot":"D:\\BLAZOR_ACC\\MyBlazorApp\\MyBlazorApp\\obj\\Debug\\net9.0\\compressed\\","BasePath":"_content/MyBlazorApp","RelativePath":"bootstrap/bootstrap.min#[.{fingerprint=bpk8xqwxhs}]?.css.gz","AssetKind":"All","AssetMode":"All","AssetRole":"Alternative","AssetMergeBehavior":null,"AssetMergeSource":"","RelatedAsset":"D:\\BLAZOR_ACC\\MyBlazorApp\\MyBlazorApp\\wwwroot\\bootstrap\\bootstrap.min.css","AssetTraitName":"Content-Encoding","AssetTraitValue":"gzip","Fingerprint":"li2ohn2azb","Integrity":"vS\u002B1ufj92SdpGYtqXPqzcZfZweLNck5DdvtrYoo0Ruc=","CopyToOutputDirectory":"Never","CopyToPublishDirectory":"PreserveNewest","OriginalItemSpec":"D:\\BLAZOR_ACC\\MyBlazorApp\\MyBlazorApp\\wwwroot\\bootstrap\\bootstrap.min.css","FileLength":23851,"LastWriteTime":"2025-12-10T00:22:59.7743419+00:00"},"xNyi3BnNDzd7DkPrP4C\u002BGZJHFXNF/hOQrz1fYDJyaoY=":{"Identity":"D:\\BLAZOR_ACC\\MyBlazorApp\\MyBlazorApp\\obj\\Debug\\net9.0\\compressed\\3bpudhqm1b-8inm30yfxf.gz","SourceId":"MyBlazorApp","SourceType":"Discovered","ContentRoot":"D:\\BLAZOR_ACC\\MyBlazorApp\\MyBlazorApp\\obj\\Debug\\net9.0\\compressed\\","BasePath":"_content/MyBlazorApp","RelativePath":"bootstrap/bootstrap.min.css#[.{fingerprint=8inm30yfxf}]?.map.gz","AssetKind":"All","AssetMode":"All","AssetRole":"Alternative","AssetMergeBehavior":null,"AssetMergeSource":"","RelatedAsset":"D:\\BLAZOR_ACC\\MyBlazorApp\\MyBlazorApp\\wwwroot\\bootstrap\\bootstrap.min.css.map","AssetTraitName":"Content-Encoding","AssetTraitValue":"gzip","Fingerprint":"m532s4naxw","Integrity":"epiz\u002BIkftKdCVrNwM3M3b4/Co3mxoqDpjOfMrHfv/7E=","CopyToOutputDirectory":"Never","CopyToPublishDirectory":"PreserveNewest","OriginalItemSpec":"D:\\BLAZOR_ACC\\MyBlazorApp\\MyBlazorApp\\wwwroot\\bootstrap\\bootstrap.min.css.map","FileLength":74642,"LastWriteTime":"2025-12-10T00:22:59.7787766+00:00"},"xkvCHP05R1a62VKwIjCz949jtXiRiOh1AkuXYpMURyY=":{"Identity":"D:\\BLAZOR_ACC\\MyBlazorApp\\MyBlazorApp\\obj\\Debug\\net9.0\\compressed\\rz458eki9x-tswichycbp.gz","SourceId":"MyBlazorApp.Client","SourceType":"Project","ContentRoot":"D:\\BLAZOR_ACC\\MyBlazorApp\\MyBlazorApp\\obj\\Debug\\net9.0\\compressed\\","BasePath":"/","RelativePath":"appsettings.Development#[.{fingerprint=tswichycbp}]?.json.gz","AssetKind":"All","AssetMode":"All","AssetRole":"Alternative","AssetMergeBehavior":null,"AssetMergeSource":"","RelatedAsset":"D:\\BLAZOR_ACC\\MyBlazorApp\\MyBlazorApp.Client\\wwwroot\\appsettings.Development.json","AssetTraitName":"Content-Encoding","AssetTraitValue":"gzip","Fingerprint":"qe8zb6ld57","Integrity":"UmgZYhCAh28IBPfRrf78XE8LMaNZsewsKDMAYtFUfWQ=","CopyToOutputDirectory":"Never","CopyToPublishDirectory":"PreserveNewest","OriginalItemSpec":"D:\\BLAZOR_ACC\\MyBlazorApp\\MyBlazorApp.Client\\wwwroot\\appsettings.Development.json","FileLength":115,"LastWriteTime":"2025-12-10T00:22:59.7712552+00:00"},"b9B6oPIK961\u002BI7DjvvftK/YG\u002BDSKes8RzH/5iXAlujY=":{"Identity":"D:\\BLAZOR_ACC\\MyBlazorApp\\MyBlazorApp\\obj\\Debug\\net9.0\\compressed\\p0vtpaet6c-tswichycbp.gz","SourceId":"MyBlazorApp.Client","SourceType":"Project","ContentRoot":"D:\\BLAZOR_ACC\\MyBlazorApp\\MyBlazorApp\\obj\\Debug\\net9.0\\compressed\\","BasePath":"/","RelativePath":"appsettings#[.{fingerprint=tswichycbp}]?.json.gz","AssetKind":"All","AssetMode":"All","AssetRole":"Alternative","AssetMergeBehavior":null,"AssetMergeSource":"","RelatedAsset":"D:\\BLAZOR_ACC\\MyBlazorApp\\MyBlazorApp.Client\\wwwroot\\appsettings.json","AssetTraitName":"Content-Encoding","AssetTraitValue":"gzip","Fingerprint":"qe8zb6ld57","Integrity":"UmgZYhCAh28IBPfRrf78XE8LMaNZsewsKDMAYtFUfWQ=","CopyToOutputDirectory":"Never","CopyToPublishDirectory":"PreserveNewest","OriginalItemSpec":"D:\\BLAZOR_ACC\\MyBlazorApp\\MyBlazorApp.Client\\wwwroot\\appsettings.json","FileLength":115,"LastWriteTime":"2025-12-10T00:22:59.7712552+00:00"},"/bCXn7HbrUgRdAT\u002BgQmRMvxLqbmR082TwgtYeplJ/yI=":{"Identity":"D:\\BLAZOR_ACC\\MyBlazorApp\\MyBlazorApp\\obj\\Debug\\net9.0\\compressed\\29sggua7h4-6zls2q3h2o.gz","SourceId":"MyBlazorApp","SourceType":"Computed","ContentRoot":"D:\\BLAZOR_ACC\\MyBlazorApp\\MyBlazorApp\\obj\\Debug\\net9.0\\compressed\\","BasePath":"_content/MyBlazorApp","RelativePath":"MyBlazorApp#[.{fingerprint=6zls2q3h2o}]?.styles.css.gz","AssetKind":"All","AssetMode":"CurrentProject","AssetRole":"Alternative","AssetMergeBehavior":null,"AssetMergeSource":"","RelatedAsset":"D:\\BLAZOR_ACC\\MyBlazorApp\\MyBlazorApp\\obj\\Debug\\net9.0\\scopedcss\\bundle\\MyBlazorApp.styles.css","AssetTraitName":"Content-Encoding","AssetTraitValue":"gzip","Fingerprint":"hcfwpn7803","Integrity":"TwUMxirub9vNUxg6ojWzb5m0X6Y8qC/0jdTWDP0cen8=","CopyToOutputDirectory":"Never","CopyToPublishDirectory":"PreserveNewest","OriginalItemSpec":"D:\\BLAZOR_ACC\\MyBlazorApp\\MyBlazorApp\\obj\\Debug\\net9.0\\scopedcss\\bundle\\MyBlazorApp.styles.css","FileLength":2004,"LastWriteTime":"2025-12-10T00:22:59.7712552+00:00"},"ZbgnHujwvCSID\u002B/9zhC5j0FgaRcc\u002BeHWGNJUhKgLx3g=":{"Identity":"D:\\BLAZOR_ACC\\MyBlazorApp\\MyBlazorApp\\obj\\Debug\\net9.0\\compressed\\pcnnvjwvb6-6zls2q3h2o.gz","SourceId":"MyBlazorApp","SourceType":"Computed","ContentRoot":"D:\\BLAZOR_ACC\\MyBlazorApp\\MyBlazorApp\\obj\\Debug\\net9.0\\compressed\\","BasePath":"_content/MyBlazorApp","RelativePath":"MyBlazorApp#[.{fingerprint=6zls2q3h2o}]!.bundle.scp.css.gz","AssetKind":"All","AssetMode":"Reference","AssetRole":"Alternative","AssetMergeBehavior":null,"AssetMergeSource":"","RelatedAsset":"D:\\BLAZOR_ACC\\MyBlazorApp\\MyBlazorApp\\obj\\Debug\\net9.0\\scopedcss\\projectbundle\\MyBlazorApp.bundle.scp.css","AssetTraitName":"Content-Encoding","AssetTraitValue":"gzip","Fingerprint":"hcfwpn7803","Integrity":"TwUMxirub9vNUxg6ojWzb5m0X6Y8qC/0jdTWDP0cen8=","CopyToOutputDirectory":"Never","CopyToPublishDirectory":"PreserveNewest","OriginalItemSpec":"D:\\BLAZOR_ACC\\MyBlazorApp\\MyBlazorApp\\obj\\Debug\\net9.0\\scopedcss\\projectbundle\\MyBlazorApp.bundle.scp.css","FileLength":2004,"LastWriteTime":"2025-12-10T00:22:59.7712552+00:00"}},"CachedCopyCandidates":{}}